edictor/__init__.py
edictor/cli.py
edictor/server.py
edictor/util.py
edictor/wordlist.py
edictor/app/config.json
edictor/app/edictor.html
edictor/app/index.html
edictor/app/css/bootstrap-select.css
edictor/app/css/bootstrap-theme.css
edictor/app/css/bootstrap.css
edictor/app/css/bootstrap.min.css
edictor/app/css/bs-excerpt.css
edictor/app/css/jquery-ui-1.10.4.custom.css
edictor/app/css/jquery-ui.css
edictor/app/css/jquery-ui.theme.css
edictor/app/css/main.css
edictor/app/css/wordlist.css
edictor/app/data/Bai.tsv
edictor/app/data/German.tsv
edictor/app/data/Germanic.tsv
edictor/app/data/Tujia.tsv
edictor/app/data/correspondence-patterns.tsv
edictor/app/data/example.tsv
edictor/app/data/filelist.csv
edictor/app/data/morpheme-glosses.tsv
edictor/app/data/conceptlists/Allen-2007-500.tsv
edictor/app/data/conceptlists/Blust-1981-200.tsv
edictor/app/data/conceptlists/Blust-2008-210.tsv
edictor/app/data/conceptlists/Comrie-1977-207.tsv
edictor/app/data/conceptlists/Norman-2003-40.tsv
edictor/app/data/conceptlists/Starostin-1991-110.tsv
edictor/app/data/conceptlists/Swadesh-1952-200.tsv
edictor/app/data/conceptlists/Swadesh-1955-100.tsv
edictor/app/fonts/glyphicons-halflings-regular.eot
edictor/app/fonts/glyphicons-halflings-regular.svg
edictor/app/fonts/glyphicons-halflings-regular.ttf
edictor/app/fonts/glyphicons-halflings-regular.woff
edictor/app/help/cognates.html
edictor/app/help/cognates.md
edictor/app/help/correspondences.md
edictor/app/help/forms.html
edictor/app/help/forms.md
edictor/app/help/ipatterns.html
edictor/app/help/ipatterns.md
edictor/app/help/make_help.py
edictor/app/help/morphology.html
edictor/app/help/morphology.md
edictor/app/help/partial.html
edictor/app/help/partial.md
edictor/app/help/patterns.html
edictor/app/help/patterns.md
edictor/app/help/phonology.html
edictor/app/help/phonology.md
edictor/app/help/sets.html
edictor/app/help/sets.md
edictor/app/help/wordlist.html
edictor/app/help/wordlist.md
edictor/app/img/edictor-small.png
edictor-3.1.dist-info/LICENSE
edictor-3.1.dist-info/METADATA
edictor-3.1.dist-info/WHEEL
edictor-3.1.dist-info/entry_points.txt
edictor-3.1.dist-info/top_level.txt
edictor-3.1.dist-info/RECORD
