Metadata-Version: 2.2
Name: edictor
Version: 3.1
Summary: Web-Based Tool for Computer-Assisted Language Comparison
Home-page: https://edictor.org
Author: Johann-Mattis List
Author-email: Johann-Mattis List <mattis.list@uni-passau.de>
Maintainer-email: Frederic Blum <frederic_blum@eva.mpg.de>, Kellen Parker van Dam <kellemparker.vandam@uni-passau.de>, Johann-Mattis List <mattis.list@uni-passau.de>
License: MIT
Project-URL: Homepage, https://edictor.org
Project-URL: Repository, https://github.com/digling/edictor.git
Keywords: linguistics,sequence alignment,computational linguistics,dialectology,cognate detection
Platform: any
Classifier: Development Status :: 5 - Production/Stable
Classifier: Intended Audience :: Developers
Classifier: Intended Audience :: Science/Research
Classifier: Natural Language :: English
Classifier: Operating System :: OS Independent
Classifier: Programming Language :: Python :: 3
Classifier: Programming Language :: Python :: 3.9
Classifier: Programming Language :: Python :: 3.10
Classifier: Programming Language :: Python :: 3.11
Classifier: Programming Language :: Python :: 3.12
Classifier: Programming Language :: Python :: Implementation :: CPython
Classifier: Programming Language :: Python :: Implementation :: PyPy
Classifier: License :: OSI Approved :: GNU General Public License v3 (GPLv3)
Requires-Python: >=3.8
License-File: LICENSE
Provides-Extra: dev
Requires-Dist: build; extra == "dev"
Requires-Dist: wheel; extra == "dev"
Requires-Dist: twine; extra == "dev"
Requires-Dist: tox; extra == "dev"
Requires-Dist: lingrex==1.4.2; extra == "dev"
Requires-Dist: lingpy==2.6.13; extra == "dev"
Requires-Dist: lexibase; extra == "dev"
Provides-Extra: test
Requires-Dist: pytest; extra == "test"
Requires-Dist: pytest-cov; extra == "test"
Requires-Dist: coverage; extra == "test"
Requires-Dist: lingpy==2.6.13; extra == "test"
Requires-Dist: lingrex==1.4.2; extra == "test"
Requires-Dist: lexibase; extra == "test"
Provides-Extra: lingpy
Requires-Dist: lingpy==2.6.13; extra == "lingpy"
Requires-Dist: lingrex==1.4.2; extra == "lingpy"
Requires-Dist: lexibase; extra == "lingpy"
